{"type":"FeatureCollection","features":[{"type":"Feature","properties":{"Facility ID":652,"Facility Name":"Hunter Holmes McGuire Veterans Administration Medical Center","VA Confirmed":61,"VA Deaths with 0":3},"geometry":{"type":"Point","coordinates":[-77.46681,37.49796]}},{"type":"Feature","properties":{"Facility ID":590,"Facility Name":"Hampton VA Medical Center","VA Confirmed":52,"VA Deaths with 0":1},"geometry":{"type":"Point","coordinates":[-76.332371,37.015768]}},{"type":"Feature","properties":{"Facility ID":658,"Facility Name":"Salem VA Medical Center","VA Confirmed":3,"VA Deaths with 0":0},"geometry":{"type":"Point","coordinates":[-80.023889,37.276111]}}]}